odoo_library/__init__.py
odoo_library/create_contact.py
odoo_library/create_rental.py
tests/__init__.py
tests/test_odoo_library.py
OdooXMLRPCLibrary-0.1.0.dist-info/LICENSE
OdooXMLRPCLibrary-0.1.0.dist-info/METADATA
OdooXMLRPCLibrary-0.1.0.dist-info/WHEEL
OdooXMLRPCLibrary-0.1.0.dist-info/entry_points.txt
OdooXMLRPCLibrary-0.1.0.dist-info/top_level.txt
OdooXMLRPCLibrary-0.1.0.dist-info/RECORD
