Metadata-Version: 2.1
Name: OdooXMLRPCLibrary
Version: 0.1.0
Summary: OdooXMLRPCLibrary is a Python library that simplifies interaction with the Odoo ERP system using XML-RPC API. With modules like create_order and create_contact, it provides an easy-to-use interface for managing rental orders and contacts in the Odoo platform. Whether youre integrating Odoo functionality into your application or automating business processes, OdooXMLRPCLibrary streamlines the communication process, making it efficient and developer-friendly.
Home-page: https://github.com/aditya-infiplus/odooXMLRPCLibrary.git
Author: Aditya Irri
Author-email: adityairri@gmail.com
License: MIT
Platform: UNKNOWN
Requires-Dist: Flask
Requires-Dist: xmlrpc
